opencode_sdk/__init__.py
opencode_sdk/cli.py
opencode_sdk/client.py
opencode_sdk/py.typed
opencode_sdk-0.2.0.dist-info/WHEEL
opencode_sdk-0.2.0.dist-info/entry_points.txt
opencode_sdk-0.2.0.dist-info/METADATA
opencode_sdk-0.2.0.dist-info/RECORD
